wpinfo/__init__.py
wpinfo/core.py
wpinfo-0.1.0.dist-info/METADATA
wpinfo-0.1.0.dist-info/WHEEL
wpinfo-0.1.0.dist-info/top_level.txt
wpinfo-0.1.0.dist-info/RECORD
